gzkeyboard/__init__.py
gzkeyboard/_modidx.py
gzkeyboard/gzkeyboard.py
gzkeyboard-0.0.1.dist-info/LICENSE
gzkeyboard-0.0.1.dist-info/METADATA
gzkeyboard-0.0.1.dist-info/WHEEL
gzkeyboard-0.0.1.dist-info/entry_points.txt
gzkeyboard-0.0.1.dist-info/top_level.txt
gzkeyboard-0.0.1.dist-info/RECORD
